_pynini.pypy311-pp73-x86_64-linux-gnu.so
_pywrapfst.pypy311-pp73-x86_64-linux-gnu.so
pynini/BUILD.bazel
pynini/__init__.py
pynini/__init__.pyi
pynini/py.typed
pynini/examples/BUILD.bazel
pynini/examples/__init__.py
pynini/examples/case.py
pynini/examples/chatspeak.py
pynini/examples/chatspeak_model.py
pynini/examples/dates.py
pynini/examples/g2p.py
pynini/examples/numbers.py
pynini/examples/plurals.py
pynini/examples/py.typed
pynini/examples/t9.py
pynini/examples/weather.py
pynini/export/BUILD.bazel
pynini/export/__init__.py
pynini/export/export.py
pynini/export/grm.py
pynini/export/grm_example.py
pynini/export/grm_py_build_defs.bzl
pynini/export/multi_grm.py
pynini/export/multi_grm_example.py
pynini/export/py.typed
pynini/lib/BUILD.bazel
pynini/lib/__init__.py
pynini/lib/byte.py
pynini/lib/edit_transducer.py
pynini/lib/features.py
pynini/lib/paradigms.py
pynini/lib/py.typed
pynini/lib/pynutil.py
pynini/lib/rewrite.py
pynini/lib/rule_cascade.py
pynini/lib/stringfile.py
pynini/lib/tagger.py
pynini/lib/utf8.py
pynini.libs/libfst-2348304c.so.26.0.0
pynini.libs/libfstfar-d8385cef.so.26.0.0
pynini.libs/libfstfarscript-1895ba25.so.26.0.0
pynini.libs/libfstmpdtscript-fe999b38.so.26.0.0
pynini.libs/libfstpdtscript-733479de.so.26.0.0
pynini.libs/libfstscript-23d14131.so.26.0.0
pywrapfst/BUILD.bazel
pywrapfst/__init__.py
pywrapfst/__init__.pyi
pywrapfst/py.typed
pynini-2.1.7.dist-info/METADATA
pynini-2.1.7.dist-info/WHEEL
pynini-2.1.7.dist-info/top_level.txt
pynini-2.1.7.dist-info/RECORD
pynini-2.1.7.dist-info/licenses/AUTHORS
pynini-2.1.7.dist-info/licenses/LICENSE
