Metadata-Version: 2.4
Name: pynini
Version: 2.1.7
Summary: Finite-state grammar compilation
Home-page: https://pynini.opengrm.org
Author: Kyle Gorman <kbg@google.com>
Author-email: kbg@google.com
License: Apache 2.0
Project-URL: homepage, https://pynini.opengrm.org
Keywords: computational linguistics,morphology,natural language processing,language
Classifier: Programming Language :: Python :: 3.8
Classifier: Programming Language :: Python :: 3.9
Classifier: Programming Language :: Python :: 3.10
Classifier: Programming Language :: Python :: 3.11
Classifier: Programming Language :: Python :: 3.12
Classifier: Development Status :: 5 - Production/Stable
Classifier: Environment :: Other Environment
Classifier: Environment :: Console
Classifier: Intended Audience :: Developers
Classifier: License :: OSI Approved :: Apache Software License
Classifier: Operating System :: OS Independent
Classifier: Topic :: Software Development :: Libraries :: Python Modules
Classifier: Topic :: Text Processing :: Linguistic
Classifier: Topic :: Scientific/Engineering :: Artificial Intelligence
Classifier: Topic :: Scientific/Engineering :: Mathematics
Requires-Python: >=3.8
License-File: LICENSE
License-File: AUTHORS
Dynamic: author-email
Dynamic: home-page
Dynamic: license-file
